aiogear/__init__.py
aiogear/admin.py
aiogear/callback_client.py
aiogear/client.py
aiogear/exception.py
aiogear/mixin.py
aiogear/packet.py
aiogear/response.py
aiogear/utils.py
aiogear/worker.py
aiogear-0.2.6.dist-info/LICENSE.txt
aiogear-0.2.6.dist-info/METADATA
aiogear-0.2.6.dist-info/RECORD
aiogear-0.2.6.dist-info/WHEEL
aiogear-0.2.6.dist-info/top_level.txt
