Metadata-Version: 2.1
Name: aiogear
Version: 0.2.6
Summary: Asynchronous gearman protocol based on asyncio
Home-page: https://github.com/sardok/aiogear
Author: Sinan Nalkaya
Author-email: sardok@gmail.com
License: UNKNOWN
Platform: UNKNOWN
Classifier: Programming Language :: Python :: 3.5
Classifier: Programming Language :: Python :: 3.6
